{
  "id": "lin_4",
  "problem": "Misalkan \\(A=\\begin{pmatrix} a & b \\\\ c & d \\end{pmatrix}\\). Tunjukan bahwa \\(A\\) memiliki dua nilai eigen berbeda yang bernilai real jika \\((a-d)^2+4bc>0\\).",
  "hints": [
    {
      "id": "h1",
      "text": "Belum ada hint."
    },
    {
      "id": "h3",
      "requires": [
        "h2"
      ],
      "text": "kocong"
    }
  ],
  "solution": "Belum ada solusi.",
  "source": "Tidak Diketahui",
  "comment": "Seleksi Kampus 2017 Aljabar Linier No. 1(b.i)"
}